CHANGES.rst
LICENSE.rst
LICENSE_LEAFLET.rst
MANIFEST.in
README.rst
setup.py
src/cone/__init__.py
src/cone.maps.egg-info/PKG-INFO
src/cone.maps.egg-info/SOURCES.txt
src/cone.maps.egg-info/dependency_links.txt
src/cone.maps.egg-info/namespace_packages.txt
src/cone.maps.egg-info/not-zip-safe
src/cone.maps.egg-info/requires.txt
src/cone.maps.egg-info/top_level.txt
src/cone/maps/__init__.py
src/cone/maps/tests.py
src/cone/maps/browser/__init__.py
src/cone/maps/browser/map.py
src/cone/maps/browser/static/cone.maps.js
src/cone/maps/browser/static/cone.maps.min.js
src/cone/maps/browser/static/leaflet/leaflet-src.js
src/cone/maps/browser/static/leaflet/leaflet-src.js.map
src/cone/maps/browser/static/leaflet/leaflet.css
src/cone/maps/browser/static/leaflet/leaflet.js
src/cone/maps/browser/static/leaflet/leaflet.js.map
src/cone/maps/browser/static/leaflet-activearea/leaflet.activearea.js
src/cone/maps/browser/static/leaflet-geosearch/geosearch.css
src/cone/maps/browser/static/leaflet-geosearch/geosearch.umd.js
src/cone/maps/browser/static/leaflet-geosearch/geosearch.umd.js.map
src/cone/maps/browser/static/leaflet-markercluster/MarkerCluster.Default.css
src/cone/maps/browser/static/leaflet-markercluster/MarkerCluster.css
src/cone/maps/browser/static/leaflet-markercluster/leaflet.markercluster-src.js
src/cone/maps/browser/static/leaflet-markercluster/leaflet.markercluster-src.js.map
src/cone/maps/browser/static/leaflet-markercluster/leaflet.markercluster.js
src/cone/maps/browser/static/leaflet-markercluster/leaflet.markercluster.js.map
src/cone/maps/browser/static/leaflet-nogap/L.TileLayer.NoGap.js
src/cone/maps/browser/static/leaflet-proj4/proj4leaflet.js
src/cone/maps/browser/static/leaflet/images/layers-2x.png
src/cone/maps/browser/static/leaflet/images/layers.png
src/cone/maps/browser/static/leaflet/images/marker-icon-2x.png
src/cone/maps/browser/static/leaflet/images/marker-icon.png
src/cone/maps/browser/static/leaflet/images/marker-shadow.png
src/cone/maps/browser/static/proj4js/proj4-src.js
src/cone/maps/browser/static/proj4js/proj4.js
src/cone/maps/locale/cone.maps.pot