Metadata-Version: 2.1
Name: cone.maps
Version: 0.1
Summary: Maps integration into cone using leaflet.js.
Home-page: http://github.com/conestack/cone.maps
Author: Cone Contributors
Author-email: dev@conestack.org
License: Simplified BSD
Keywords: node pyramid cone web
Platform: UNKNOWN
Classifier: Environment :: Web Environment
Classifier: Programming Language :: Python
Classifier: Topic :: Internet :: WWW/HTTP :: Dynamic Content
Provides-Extra: test
